{"argGroups":[{"args":[{"format":{"maxLength":50,"minLength":5,"pattern":"^[a-zA-Z0-9_-]*$"},"help":{"short":"The name of the configuration store."},"idPart":"name","options":["config-store-name"],"required":true,"type":"string","var":"$Path.configStoreName"},{"help":{"short":"Identifier of key and label combination. Key and label are joined by $ character. Label is optional."},"idPart":"child_name_1","options":["n","name","key-value-name"],"required":true,"type":"string","var":"$Path.keyValueName"},{"idPart":"resource_group","options":["g","resource-group"],"required":true,"type":"ResourceGroupName","var":"$Path.resourceGroupName"},{"idPart":"subscription","options":["subscription"],"required":true,"type":"SubscriptionId","var":"$Path.subscriptionId"}],"name":""}],"confirmation":"Are you sure you want to perform this operation?","operations":[{"http":{"path":"/subscriptions/{subscriptionId}/resourceGroups/{resourceGroupName}/providers/Microsoft.AppConfiguration/configurationStores/{configStoreName}/keyValues/{keyValueName}","request":{"method":"delete","path":{"params":[{"arg":"$Path.configStoreName","format":{"maxLength":50,"minLength":5,"pattern":"^[a-zA-Z0-9_-]*$"},"name":"configStoreName","required":true,"type":"string"},{"arg":"$Path.keyValueName","name":"keyValueName","required":true,"type":"string"},{"arg":"$Path.resourceGroupName","name":"resourceGroupName","required":true,"type":"string"},{"arg":"$Path.subscriptionId","name":"subscriptionId","required":true,"type":"string"}]},"query":{"consts":[{"const":true,"default":{"value":"2022-05-01"},"name":"api-version","readOnly":true,"required":true,"type":"string"}]}},"responses":[{"statusCode":[200]},{"statusCode":[202]},{"statusCode":[204]},{"body":{"json":{"schema":{"type":"@MgmtErrorFormat"}}},"isError":true},{"body":{"json":{"schema":{"type":"@MgmtErrorFormat"}}},"isError":true}]},"longRunning":{"finalStateVia":"azure-async-operation"},"operationId":"KeyValues_Delete"}],"resources":[{"id":"/subscriptions/{}/resourcegroups/{}/providers/microsoft.appconfiguration/configurationstores/{}/keyvalues/{}","plane":"mgmt-plane"}]}