{"argGroups":[{"args":[{"help":{"short":"Unique identifier for the product family"},"idPart":"child_name_1","options":["family-identifier"],"required":true,"type":"string","var":"$Path.familyIdentifier"},{"idPart":"name","options":["l","location"],"required":true,"type":"ResourceLocation","var":"$Path.location"},{"help":{"short":"The serial number of the device"},"idPart":"child_name_2","options":["serial-number"],"required":true,"type":"string","var":"$Path.serialNumber"},{"idPart":"subscription","options":["subscription"],"required":true,"type":"SubscriptionId","var":"$Path.subscriptionId"}],"name":""},{"args":[{"args":[{"help":{"short":"Configuration identifier on device"},"options":["configuration-identifier"],"required":true,"type":"string","var":"$manageInventoryMetadataRequest.configurationOnDevice.configurationIdentifier"}],"group":"ManageInventoryMetadataRequest","help":{"short":"Inventory configuration to be updated"},"options":["configuration-on-device"],"type":"object","var":"$manageInventoryMetadataRequest.configurationOnDevice"},{"group":"ManageInventoryMetadataRequest","help":{"short":"Inventory metadata to be updated"},"options":["inventory-metadata"],"required":true,"type":"string","var":"$manageInventoryMetadataRequest.inventoryMetadata"}],"name":"ManageInventoryMetadataRequest"}],"operations":[{"http":{"path":"/subscriptions/{subscriptionId}/providers/Microsoft.EdgeOrderPartner/locations/{location}/productFamilies/{familyIdentifier}/inventories/{serialNumber}/manageInventoryMetadata","request":{"body":{"json":{"schema":{"clientFlatten":true,"name":"manageInventoryMetadataRequest","props":[{"arg":"$manageInventoryMetadataRequest.configurationOnDevice","name":"configurationOnDevice","props":[{"arg":"$manageInventoryMetadataRequest.configurationOnDevice.configurationIdentifier","name":"configurationIdentifier","required":true,"type":"string"}],"type":"object"},{"arg":"$manageInventoryMetadataRequest.inventoryMetadata","name":"inventoryMetadata","required":true,"type":"string"}],"required":true,"type":"object"}}},"method":"post","path":{"params":[{"arg":"$Path.familyIdentifier","name":"familyIdentifier","required":true,"type":"string"},{"arg":"$Path.location","name":"location","required":true,"type":"string"},{"arg":"$Path.serialNumber","name":"serialNumber","required":true,"type":"string"},{"arg":"$Path.subscriptionId","format":{"minLength":1},"name":"subscriptionId","required":true,"type":"string"}]},"query":{"consts":[{"const":true,"default":{"value":"2020-12-01-preview"},"format":{"minLength":1},"name":"api-version","readOnly":true,"required":true,"type":"string"}]}},"responses":[{"statusCode":[200]},{"statusCode":[202]},{"statusCode":[204]},{"body":{"json":{"schema":{"type":"@MgmtErrorFormat"}}},"isError":true},{"body":{"json":{"schema":{"type":"@MgmtErrorFormat"}}},"isError":true}]},"longRunning":{"finalStateVia":"azure-async-operation"},"operationId":"ManageInventoryMetadata"}],"resources":[{"id":"/subscriptions/{}/providers/microsoft.edgeorderpartner/locations/{}/productfamilies/{}/inventories/{}/manageinventorymetadata","plane":"mgmt-plane"}]}