{"argGroups":[{"args":[{"format":{"maxLength":54,"minLength":1,"pattern":"^[a-zA-Z0-9-_\\.]{1,54}$"},"help":{"short":"The name of the machine."},"idPart":"name","options":["machine-name"],"required":true,"type":"string","var":"$Path.machineName"},{"idPart":"resource_group","options":["g","resource-group"],"required":true,"type":"ResourceGroupName","var":"$Path.resourceGroupName"},{"idPart":"subscription","options":["subscription"],"required":true,"type":"SubscriptionId","var":"$Path.subscriptionId"}],"name":""}],"operations":[{"http":{"path":"/subscriptions/{subscriptionId}/resourceGroups/{resourceGroupName}/providers/Microsoft.HybridCompute/machines/{machineName}/licenseProfiles","request":{"method":"get","path":{"params":[{"arg":"$Path.machineName","format":{"maxLength":54,"minLength":1,"pattern":"^[a-zA-Z0-9-_\\.]{1,54}$"},"name":"machineName","required":true,"type":"string"},{"arg":"$Path.resourceGroupName","format":{"maxLength":90,"minLength":1},"name":"resourceGroupName","required":true,"type":"string"},{"arg":"$Path.subscriptionId","format":{"minLength":1},"name":"subscriptionId","required":true,"type":"string"}]},"query":{"consts":[{"const":true,"default":{"value":"2024-03-31-preview"},"format":{"minLength":1},"name":"api-version","readOnly":true,"required":true,"type":"string"}]}},"responses":[{"body":{"json":{"schema":{"props":[{"name":"nextLink","type":"string"},{"item":{"props":[{"format":{"template":"/subscriptions/{}/resourceGroups/{}/providers/Microsoft.HybridCompute/machines/{}/licenseProfiles/{}"},"name":"id","readOnly":true,"type":"ResourceId"},{"name":"location","required":true,"type":"ResourceLocation"},{"name":"name","readOnly":true,"type":"string"},{"clientFlatten":true,"name":"properties","props":[{"clientFlatten":true,"name":"esuProfile","props":[{"name":"assignedLicense","type":"string"},{"name":"assignedLicenseImmutableId","readOnly":true,"type":"string"},{"enum":{"items":[{"value":"Eligible"},{"value":"Ineligible"},{"value":"Unknown"}]},"name":"esuEligibility","readOnly":true,"type":"string"},{"enum":{"items":[{"value":"Active"},{"value":"Inactive"}]},"name":"esuKeyState","readOnly":true,"type":"string"},{"item":{"props":[{"name":"licenseStatus","type":"integer32"},{"name":"sku","type":"string"}],"type":"object"},"name":"esuKeys","readOnly":true,"type":"array<object>"},{"enum":{"items":[{"value":"Datacenter"},{"value":"Standard"}]},"name":"serverType","readOnly":true,"type":"string"}],"type":"object"},{"clientFlatten":true,"name":"productProfile","props":[{"format":{"protocol":"iso"},"name":"billingStartDate","readOnly":true,"type":"dateTime"},{"format":{"protocol":"iso"},"name":"disenrollmentDate","readOnly":true,"type":"dateTime"},{"format":{"protocol":"iso"},"name":"enrollmentDate","readOnly":true,"type":"dateTime"},{"item":{"props":[{"format":{"protocol":"iso"},"name":"billingStartDate","readOnly":true,"type":"dateTime"},{"format":{"protocol":"iso"},"name":"disenrollmentDate","readOnly":true,"type":"dateTime"},{"format":{"protocol":"iso"},"name":"enrollmentDate","readOnly":true,"type":"dateTime"},{"name":"name","type":"string"},{"enum":{"items":[{"value":"Disabled"},{"value":"Enabled"},{"value":"Enabling"},{"value":"Unknown"}]},"name":"subscriptionStatus","type":"string"}],"type":"object"},"name":"productFeatures","type":"array<object>"},{"enum":{"items":[{"value":"WindowsIoTEnterprise"},{"value":"WindowsServer"}]},"name":"productType","type":"string"},{"enum":{"items":[{"value":"Disabled"},{"value":"Enabled"},{"value":"Enabling"},{"value":"Unknown"}]},"name":"subscriptionStatus","type":"string"}],"type":"object"},{"enum":{"items":[{"value":"Accepted"},{"value":"Canceled"},{"value":"Creating"},{"value":"Deleted"},{"value":"Deleting"},{"value":"Failed"},{"value":"Succeeded"},{"value":"Updating"}]},"name":"provisioningState","readOnly":true,"type":"string"},{"clientFlatten":true,"name":"softwareAssurance","props":[{"name":"softwareAssuranceCustomer","type":"boolean"}],"type":"object"}],"type":"object"},{"name":"systemData","props":[{"format":{"protocol":"iso"},"name":"createdAt","type":"dateTime"},{"name":"createdBy","type":"string"},{"enum":{"items":[{"value":"Application"},{"value":"Key"},{"value":"ManagedIdentity"},{"value":"User"}]},"name":"createdByType","type":"string"},{"format":{"protocol":"iso"},"name":"lastModifiedAt","type":"dateTime"},{"name":"lastModifiedBy","type":"string"},{"enum":{"items":[{"value":"Application"},{"value":"Key"},{"value":"ManagedIdentity"},{"value":"User"}]},"name":"lastModifiedByType","type":"string"}],"readOnly":true,"type":"object"},{"additionalProps":{"item":{"type":"string"}},"name":"tags","type":"object"},{"name":"type","readOnly":true,"type":"string"}],"type":"object"},"name":"value","required":true,"type":"array<object>"}],"type":"object"},"var":"$Instance"}},"statusCode":[200]},{"body":{"json":{"schema":{"type":"@MgmtErrorFormat"}}},"isError":true},{"body":{"json":{"schema":{"type":"@MgmtErrorFormat"}}},"isError":true}]},"operationId":"LicenseProfiles_List"}],"outputs":[{"clientFlatten":true,"nextLink":"$Instance.nextLink","ref":"$Instance.value","type":"array"}],"resources":[{"id":"/subscriptions/{}/resourcegroups/{}/providers/microsoft.hybridcompute/machines/{}/licenseprofiles","plane":"mgmt-plane"}]}