{"argGroups":[{"args":[{"format":{"pattern":"^[-a-zA-Z0-9_]{1,50}$"},"help":{"short":"Report Name."},"options":["report-name"],"required":true,"type":"string","var":"$Path.reportName"},{"format":{"pattern":"^[-a-zA-Z0-9_]{1,50}$"},"help":{"short":"Webhook Name."},"options":["webhook-name"],"required":true,"type":"string","var":"$Path.webhookName"}],"name":""}],"confirmation":"Are you sure you want to perform this operation?","operations":[{"http":{"path":"/providers/Microsoft.AppComplianceAutomation/reports/{reportName}/webhooks/{webhookName}","request":{"method":"delete","path":{"params":[{"arg":"$Path.reportName","format":{"pattern":"^[-a-zA-Z0-9_]{1,50}$"},"name":"reportName","required":true,"type":"string"},{"arg":"$Path.webhookName","format":{"pattern":"^[-a-zA-Z0-9_]{1,50}$"},"name":"webhookName","required":true,"type":"string"}]},"query":{"consts":[{"const":true,"default":{"value":"2024-06-27"},"format":{"minLength":1},"name":"api-version","readOnly":true,"required":true,"type":"string"}]}},"responses":[{"statusCode":[200]},{"statusCode":[204]},{"body":{"json":{"schema":{"type":"@MgmtErrorFormat"}}},"isError":true},{"body":{"json":{"schema":{"type":"@MgmtErrorFormat"}}},"isError":true}]},"operationId":"Webhook_Delete"}],"resources":[{"id":"/providers/microsoft.appcomplianceautomation/reports/{}/webhooks/{}","plane":"mgmt-plane"}]}