{"argGroups":[{"args":[{"group":"Parameters","help":{"short":"The resource type."},"options":["type"],"type":"string","var":"$parameters.type"}],"name":"Parameters"}],"operations":[{"http":{"path":"/providers/Microsoft.AppComplianceAutomation/getCollectionCount","request":{"body":{"json":{"schema":{"clientFlatten":true,"name":"parameters","props":[{"arg":"$parameters.type","name":"type","type":"string"}],"required":true,"type":"object"}}},"method":"post","query":{"consts":[{"const":true,"default":{"value":"2024-06-27"},"format":{"minLength":1},"name":"api-version","readOnly":true,"required":true,"type":"string"}]}},"responses":[{"body":{"json":{"schema":{"props":[{"name":"count","type":"integer32"}],"type":"object"},"var":"$Instance"}},"statusCode":[200]},{"body":{"json":{"schema":{"type":"@MgmtErrorFormat"}}},"isError":true},{"body":{"json":{"schema":{"type":"@MgmtErrorFormat"}}},"isError":true}]},"operationId":"ProviderActions_GetCollectionCount"}],"outputs":[{"clientFlatten":true,"ref":"$Instance","type":"object"}],"resources":[{"id":"/providers/microsoft.appcomplianceautomation/getcollectioncount","plane":"mgmt-plane"}]}