{"argGroups":[{"args":[{"idPart":"subscription","options":["subscription"],"required":true,"type":"SubscriptionId","var":"$Path.subscriptionId"}],"name":""},{"args":[{"group":"NameAvailabilityParameters","help":{"short":"The CommunicationService name to validate. e.g.\"my-CommunicationService-name-here\""},"options":["name"],"type":"string","var":"$nameAvailabilityParameters.name"},{"group":"NameAvailabilityParameters","help":{"short":"The resource type. Should be always \"Microsoft.Communication/CommunicationServices\"."},"options":["type"],"type":"string","var":"$nameAvailabilityParameters.type"}],"name":"NameAvailabilityParameters"}],"operations":[{"http":{"path":"/subscriptions/{subscriptionId}/providers/Microsoft.Communication/checkNameAvailability","request":{"body":{"json":{"schema":{"clientFlatten":true,"name":"nameAvailabilityParameters","props":[{"arg":"$nameAvailabilityParameters.name","name":"name","required":true,"type":"string"},{"arg":"$nameAvailabilityParameters.type","name":"type","required":true,"type":"string"}],"type":"object"}}},"method":"post","path":{"params":[{"arg":"$Path.subscriptionId","format":{"minLength":1},"name":"subscriptionId","required":true,"type":"string"}]},"query":{"consts":[{"const":true,"default":{"value":"2020-08-20"},"format":{"minLength":1},"name":"api-version","readOnly":true,"required":true,"type":"string"}]}},"responses":[{"body":{"json":{"schema":{"props":[{"name":"message","type":"string"},{"name":"nameAvailable","type":"boolean"},{"name":"reason","type":"string"}],"type":"object"},"var":"$Instance"}},"statusCode":[200]},{"body":{"json":{"schema":{"type":"@MgmtErrorFormat"}}},"isError":true},{"body":{"json":{"schema":{"type":"@MgmtErrorFormat"}}},"isError":true}]},"operationId":"CommunicationService_CheckNameAvailability"}],"outputs":[{"clientFlatten":true,"ref":"$Instance","type":"object"}],"resources":[{"id":"/subscriptions/{}/providers/microsoft.communication/checknameavailability","plane":"mgmt-plane"}]}