{"argGroups":[{"args":[{"idPart":"resource_group","options":["g","resource-group"],"required":true,"type":"ResourceGroupName","var":"$Path.resourceGroupName"},{"format":{"maxLength":63,"minLength":1,"pattern":"^[a-zA-Z0-9]$|^[a-zA-Z0-9][-_a-zA-Z0-9]{0,61}[a-zA-Z0-9]$"},"help":{"short":"The name of the managed cluster resource."},"idPart":"name","options":["n","name","resource-name"],"required":true,"type":"string","var":"$Path.resourceName"},{"idPart":"subscription","options":["subscription"],"required":true,"type":"SubscriptionId","var":"$Path.subscriptionId"}],"name":""},{"args":[{"additionalProps":{"item":{"type":"string"}},"group":"Parameters","help":{"short":"Resource tags."},"options":["tags"],"type":"object","var":"$parameters.tags"}],"name":"Parameters"}],"operations":[{"http":{"path":"/subscriptions/{subscriptionId}/resourceGroups/{resourceGroupName}/providers/Microsoft.ContainerService/managedClusters/{resourceName}","request":{"body":{"json":{"schema":{"clientFlatten":true,"name":"parameters","props":[{"additionalProps":{"item":{"type":"string"}},"arg":"$parameters.tags","name":"tags","type":"object"}],"required":true,"type":"object"}}},"method":"patch","path":{"params":[{"arg":"$Path.resourceGroupName","format":{"maxLength":90,"minLength":1},"name":"resourceGroupName","required":true,"type":"string"},{"arg":"$Path.resourceName","format":{"maxLength":63,"minLength":1,"pattern":"^[a-zA-Z0-9]$|^[a-zA-Z0-9][-_a-zA-Z0-9]{0,61}[a-zA-Z0-9]$"},"name":"resourceName","required":true,"type":"string"},{"arg":"$Path.subscriptionId","format":{"minLength":1},"name":"subscriptionId","required":true,"type":"string"}]},"query":{"consts":[{"const":true,"default":{"value":"2022-07-01"},"format":{"minLength":1},"name":"api-version","readOnly":true,"required":true,"type":"string"}]}},"responses":[{"body":{"json":{"schema":{"props":[{"name":"extendedLocation","props":[{"name":"name","type":"string"},{"enum":{"items":[{"value":"EdgeZone"}]},"name":"type","type":"string"}],"type":"object"},{"format":{"template":"/subscriptions/{}/resourceGroups/{}/providers/Microsoft.ContainerService/managedClusters/{}"},"name":"id","readOnly":true,"type":"ResourceId"},{"name":"identity","props":[{"name":"principalId","readOnly":true,"type":"string"},{"name":"tenantId","readOnly":true,"type":"string"},{"enum":{"items":[{"value":"None"},{"value":"SystemAssigned"},{"value":"UserAssigned"}]},"name":"type","type":"string"},{"additionalProps":{"item":{"props":[{"name":"clientId","readOnly":true,"type":"string"},{"name":"principalId","readOnly":true,"type":"string"}],"type":"object"}},"name":"userAssignedIdentities","type":"object"}],"type":"IdentityObject"},{"name":"location","required":true,"type":"ResourceLocation"},{"name":"name","readOnly":true,"type":"string"},{"clientFlatten":true,"name":"properties","props":[{"name":"aadProfile","props":[{"item":{"type":"string"},"name":"adminGroupObjectIDs","type":"array<string>"},{"name":"clientAppID","type":"string"},{"name":"enableAzureRBAC","type":"boolean"},{"name":"managed","type":"boolean"},{"name":"serverAppID","type":"string"},{"name":"serverAppSecret","type":"string"},{"name":"tenantID","type":"string"}],"type":"object"},{"additionalProps":{"item":{"props":[{"additionalProps":{"item":{"type":"string"}},"name":"config","type":"object"},{"name":"enabled","required":true,"type":"boolean"},{"name":"identity","props":[{"name":"clientId","type":"string"},{"name":"objectId","type":"string"},{"name":"resourceId","type":"ResourceId"}],"readOnly":true,"type":"object"}],"type":"object"}},"name":"addonProfiles","type":"object"},{"item":{"props":[{"item":{"type":"string"},"name":"availabilityZones","type":"array<string>"},{"name":"count","type":"integer32"},{"name":"creationData","props":[{"name":"sourceResourceId","type":"ResourceId"}],"type":"object"},{"name":"currentOrchestratorVersion","readOnly":true,"type":"string"},{"name":"enableAutoScaling","type":"boolean"},{"name":"enableEncryptionAtHost","type":"boolean"},{"name":"enableFIPS","type":"boolean"},{"name":"enableNodePublicIP","type":"boolean"},{"name":"enableUltraSSD","type":"boolean"},{"enum":{"items":[{"value":"MIG1g"},{"value":"MIG2g"},{"value":"MIG3g"},{"value":"MIG4g"},{"value":"MIG7g"}]},"name":"gpuInstanceProfile","type":"string"},{"name":"hostGroupID","type":"ResourceId"},{"name":"kubeletConfig","props":[{"item":{"type":"string"},"name":"allowedUnsafeSysctls","type":"array<string>"},{"format":{"minimum":2},"name":"containerLogMaxFiles","type":"integer32"},{"name":"containerLogMaxSizeMB","type":"integer32"},{"name":"cpuCfsQuota","type":"boolean"},{"name":"cpuCfsQuotaPeriod","type":"string"},{"name":"cpuManagerPolicy","type":"string"},{"name":"failSwapOn","type":"boolean"},{"name":"imageGcHighThreshold","type":"integer32"},{"name":"imageGcLowThreshold","type":"integer32"},{"name":"podMaxPids","type":"integer32"},{"name":"topologyManagerPolicy","type":"string"}],"type":"object"},{"enum":{"items":[{"value":"OS"},{"value":"Temporary"}]},"name":"kubeletDiskType","type":"string"},{"name":"linuxOSConfig","props":[{"name":"swapFileSizeMB","type":"integer32"},{"name":"sysctls","props":[{"name":"fsAioMaxNr","type":"integer32"},{"name":"fsFileMax","type":"integer32"},{"name":"fsInotifyMaxUserWatches","type":"integer32"},{"name":"fsNrOpen","type":"integer32"},{"name":"kernelThreadsMax","type":"integer32"},{"name":"netCoreNetdevMaxBacklog","type":"integer32"},{"name":"netCoreOptmemMax","type":"integer32"},{"name":"netCoreRmemDefault","type":"integer32"},{"name":"netCoreRmemMax","type":"integer32"},{"name":"netCoreSomaxconn","type":"integer32"},{"name":"netCoreWmemDefault","type":"integer32"},{"name":"netCoreWmemMax","type":"integer32"},{"name":"netIpv4IpLocalPortRange","type":"string"},{"name":"netIpv4NeighDefaultGcThresh1","type":"integer32"},{"name":"netIpv4NeighDefaultGcThresh2","type":"integer32"},{"name":"netIpv4NeighDefaultGcThresh3","type":"integer32"},{"name":"netIpv4TcpFinTimeout","type":"integer32"},{"name":"netIpv4TcpKeepaliveProbes","type":"integer32"},{"name":"netIpv4TcpKeepaliveTime","type":"integer32"},{"name":"netIpv4TcpMaxSynBacklog","type":"integer32"},{"name":"netIpv4TcpMaxTwBuckets","type":"integer32"},{"name":"netIpv4TcpTwReuse","type":"boolean"},{"name":"netIpv4TcpkeepaliveIntvl","type":"integer32"},{"name":"netNetfilterNfConntrackBuckets","type":"integer32"},{"name":"netNetfilterNfConntrackMax","type":"integer32"},{"name":"vmMaxMapCount","type":"integer32"},{"name":"vmSwappiness","type":"integer32"},{"name":"vmVfsCachePressure","type":"integer32"}],"type":"object"},{"name":"transparentHugePageDefrag","type":"string"},{"name":"transparentHugePageEnabled","type":"string"}],"type":"object"},{"name":"maxCount","type":"integer32"},{"name":"maxPods","type":"integer32"},{"name":"minCount","type":"integer32"},{"enum":{"items":[{"value":"System"},{"value":"User"}]},"name":"mode","type":"string"},{"format":{"pattern":"^[a-z][a-z0-9]{0,11}$"},"name":"name","required":true,"type":"string"},{"name":"nodeImageVersion","readOnly":true,"type":"string"},{"additionalProps":{"item":{"type":"string"}},"name":"nodeLabels","type":"object"},{"name":"nodePublicIPPrefixID","type":"ResourceId"},{"item":{"type":"string"},"name":"nodeTaints","type":"array<string>"},{"name":"orchestratorVersion","type":"string"},{"format":{"maximum":2048,"minimum":0},"name":"osDiskSizeGB","type":"integer32"},{"enum":{"items":[{"value":"Ephemeral"},{"value":"Managed"}]},"name":"osDiskType","type":"string"},{"enum":{"items":[{"value":"CBLMariner"},{"value":"Ubuntu"},{"value":"Windows2019"},{"value":"Windows2022"}]},"name":"osSKU","type":"string"},{"default":{"value":"Linux"},"enum":{"items":[{"value":"Linux"},{"value":"Windows"}]},"name":"osType","type":"string"},{"name":"podSubnetID","type":"ResourceId"},{"name":"powerState","type":"@PowerState_read"},{"name":"provisioningState","readOnly":true,"type":"string"},{"name":"proximityPlacementGroupID","type":"ResourceId"},{"enum":{"items":[{"value":"Deallocate"},{"value":"Delete"}]},"name":"scaleDownMode","type":"string"},{"default":{"value":"Delete"},"enum":{"items":[{"value":"Deallocate"},{"value":"Delete"}]},"name":"scaleSetEvictionPolicy","type":"string"},{"default":{"value":"Regular"},"enum":{"items":[{"value":"Regular"},{"value":"Spot"}]},"name":"scaleSetPriority","type":"string"},{"default":{"value":-1},"name":"spotMaxPrice","type":"float"},{"additionalProps":{"item":{"type":"string"}},"name":"tags","type":"object"},{"enum":{"items":[{"value":"AvailabilitySet"},{"value":"VirtualMachineScaleSets"}]},"name":"type","type":"string"},{"name":"upgradeSettings","props":[{"name":"maxSurge","type":"string"}],"type":"object"},{"name":"vmSize","type":"string"},{"name":"vnetSubnetID","type":"ResourceId"},{"enum":{"items":[{"value":"OCIContainer"},{"value":"WasmWasi"}]},"name":"workloadRuntime","type":"string"}],"type":"object"},"name":"agentPoolProfiles","type":"array<object>"},{"name":"apiServerAccessProfile","props":[{"item":{"type":"string"},"name":"authorizedIPRanges","type":"array<string>"},{"name":"disableRunCommand","type":"boolean"},{"name":"enablePrivateCluster","type":"boolean"},{"name":"enablePrivateClusterPublicFQDN","type":"boolean"},{"name":"privateDNSZone","type":"string"}],"type":"object"},{"name":"autoScalerProfile","props":[{"name":"balance-similar-node-groups","type":"string"},{"enum":{"items":[{"value":"least-waste"},{"value":"most-pods"},{"value":"priority"},{"value":"random"}]},"name":"expander","type":"string"},{"name":"max-empty-bulk-delete","type":"string"},{"name":"max-graceful-termination-sec","type":"string"},{"name":"max-node-provision-time","type":"string"},{"name":"max-total-unready-percentage","type":"string"},{"name":"new-pod-scale-up-delay","type":"string"},{"name":"ok-total-unready-count","type":"string"},{"name":"scale-down-delay-after-add","type":"string"},{"name":"scale-down-delay-after-delete","type":"string"},{"name":"scale-down-delay-after-failure","type":"string"},{"name":"scale-down-unneeded-time","type":"string"},{"name":"scale-down-unready-time","type":"string"},{"name":"scale-down-utilization-threshold","type":"string"},{"name":"scan-interval","type":"string"},{"name":"skip-nodes-with-local-storage","type":"string"},{"name":"skip-nodes-with-system-pods","type":"string"}],"type":"object"},{"name":"autoUpgradeProfile","props":[{"enum":{"items":[{"value":"node-image"},{"value":"none"},{"value":"patch"},{"value":"rapid"},{"value":"stable"}]},"name":"upgradeChannel","type":"string"}],"type":"object"},{"name":"azurePortalFQDN","readOnly":true,"type":"string"},{"name":"currentKubernetesVersion","readOnly":true,"type":"string"},{"name":"disableLocalAccounts","type":"boolean"},{"name":"diskEncryptionSetID","type":"ResourceId"},{"name":"dnsPrefix","type":"string"},{"name":"enablePodSecurityPolicy","type":"boolean"},{"name":"enableRBAC","type":"boolean"},{"name":"fqdn","readOnly":true,"type":"string"},{"name":"fqdnSubdomain","type":"string"},{"name":"httpProxyConfig","props":[{"name":"httpProxy","type":"string"},{"name":"httpsProxy","type":"string"},{"item":{"type":"string"},"name":"noProxy","type":"array<string>"},{"name":"trustedCa","type":"string"}],"type":"object"},{"additionalProps":{"item":{"type":"@UserAssignedIdentity_read"}},"name":"identityProfile","type":"object"},{"name":"kubernetesVersion","type":"string"},{"name":"linuxProfile","props":[{"format":{"pattern":"^[A-Za-z][-A-Za-z0-9_]*$"},"name":"adminUsername","required":true,"type":"string"},{"name":"ssh","props":[{"item":{"props":[{"name":"keyData","required":true,"type":"string"}],"type":"object"},"name":"publicKeys","required":true,"type":"array<object>"}],"required":true,"type":"object"}],"type":"object"},{"name":"maxAgentPools","readOnly":true,"type":"integer32"},{"name":"networkProfile","props":[{"default":{"value":"10.0.0.10"},"format":{"pattern":"^(?:(?:25[0-5]|2[0-4][0-9]|[01]?[0-9][0-9]?)\\.){3}(?:25[0-5]|2[0-4][0-9]|[01]?[0-9][0-9]?)$"},"name":"dnsServiceIP","type":"string"},{"default":{"value":"172.17.0.1/16"},"format":{"pattern":"^([0-9]{1,3}\\.){3}[0-9]{1,3}(\\/([0-9]|[1-2][0-9]|3[0-2]))?$"},"name":"dockerBridgeCidr","type":"string"},{"item":{"enum":{"items":[{"value":"IPv4"},{"value":"IPv6"}]},"type":"string"},"name":"ipFamilies","type":"array<string>"},{"name":"loadBalancerProfile","props":[{"default":{"value":0},"format":{"maximum":64000,"minimum":0},"name":"allocatedOutboundPorts","type":"integer32"},{"item":{"type":"@ResourceReference_read"},"name":"effectiveOutboundIPs","type":"array<@ResourceReference_read>"},{"name":"enableMultipleStandardLoadBalancers","type":"boolean"},{"default":{"value":30},"format":{"maximum":120,"minimum":4},"name":"idleTimeoutInMinutes","type":"integer32"},{"name":"managedOutboundIPs","props":[{"default":{"value":1},"format":{"maximum":100,"minimum":1},"name":"count","type":"integer32"},{"default":{"value":0},"format":{"maximum":100,"minimum":0},"name":"countIPv6","type":"integer32"}],"type":"object"},{"name":"outboundIPPrefixes","props":[{"item":{"cls":"ResourceReference_read","props":[{"name":"id","type":"ResourceId"}],"type":"object"},"name":"publicIPPrefixes","type":"array<object>"}],"type":"object"},{"name":"outboundIPs","props":[{"item":{"type":"@ResourceReference_read"},"name":"publicIPs","type":"array<@ResourceReference_read>"}],"type":"object"}],"type":"object"},{"enum":{"items":[{"value":"basic"},{"value":"standard"}]},"name":"loadBalancerSku","type":"string"},{"name":"natGatewayProfile","props":[{"item":{"type":"@ResourceReference_read"},"name":"effectiveOutboundIPs","type":"array<@ResourceReference_read>"},{"default":{"value":4},"format":{"maximum":120,"minimum":4},"name":"idleTimeoutInMinutes","type":"integer32"},{"name":"managedOutboundIPProfile","props":[{"default":{"value":1},"format":{"maximum":16,"minimum":1},"name":"count","type":"integer32"}],"type":"object"}],"type":"object"},{"enum":{"items":[{"value":"bridge"},{"value":"transparent"}]},"name":"networkMode","type":"string"},{"default":{"value":"kubenet"},"enum":{"items":[{"value":"azure"},{"value":"kubenet"},{"value":"none"}]},"name":"networkPlugin","type":"string"},{"enum":{"items":[{"value":"azure"},{"value":"calico"}]},"name":"networkPolicy","type":"string"},{"default":{"value":"loadBalancer"},"enum":{"items":[{"value":"loadBalancer"},{"value":"managedNATGateway"},{"value":"userAssignedNATGateway"},{"value":"userDefinedRouting"}]},"name":"outboundType","type":"string"},{"default":{"value":"10.244.0.0/16"},"format":{"pattern":"^([0-9]{1,3}\\.){3}[0-9]{1,3}(\\/([0-9]|[1-2][0-9]|3[0-2]))?$"},"name":"podCidr","type":"string"},{"item":{"type":"string"},"name":"podCidrs","type":"array<string>"},{"default":{"value":"10.0.0.0/16"},"format":{"pattern":"^([0-9]{1,3}\\.){3}[0-9]{1,3}(\\/([0-9]|[1-2][0-9]|3[0-2]))?$"},"name":"serviceCidr","type":"string"},{"item":{"type":"string"},"name":"serviceCidrs","type":"array<string>"}],"type":"object"},{"name":"nodeResourceGroup","type":"string"},{"name":"podIdentityProfile","props":[{"name":"allowNetworkPluginKubenet","type":"boolean"},{"name":"enabled","type":"boolean"},{"item":{"props":[{"name":"bindingSelector","type":"string"},{"cls":"UserAssignedIdentity_read","name":"identity","props":[{"name":"clientId","type":"string"},{"name":"objectId","type":"string"},{"name":"resourceId","type":"ResourceId"}],"required":true,"type":"object"},{"name":"name","required":true,"type":"string"},{"name":"namespace","required":true,"type":"string"},{"name":"provisioningInfo","props":[{"name":"error","props":[{"cls":"ManagedClusterPodIdentityProvisioningErrorBody_read","name":"error","props":[{"name":"code","type":"string"},{"item":{"type":"@ManagedClusterPodIdentityProvisioningErrorBody_read"},"name":"details","type":"array<@ManagedClusterPodIdentityProvisioningErrorBody_read>"},{"name":"message","type":"string"},{"name":"target","type":"string"}],"type":"object"}],"type":"object"}],"readOnly":true,"type":"object"},{"enum":{"items":[{"value":"Assigned"},{"value":"Deleting"},{"value":"Failed"},{"value":"Updating"}]},"name":"provisioningState","readOnly":true,"type":"string"}],"type":"object"},"name":"userAssignedIdentities","type":"array<object>"},{"item":{"props":[{"name":"name","required":true,"type":"string"},{"name":"namespace","required":true,"type":"string"},{"additionalProps":{"item":{"type":"string"}},"name":"podLabels","required":true,"type":"object"}],"type":"object"},"name":"userAssignedIdentityExceptions","type":"array<object>"}],"type":"object"},{"cls":"PowerState_read","name":"powerState","props":[{"enum":{"items":[{"value":"Running"},{"value":"Stopped"}]},"name":"code","type":"string"}],"readOnly":true,"type":"object"},{"name":"privateFQDN","readOnly":true,"type":"string"},{"item":{"props":[{"name":"groupId","type":"string"},{"name":"id","type":"string"},{"name":"name","type":"string"},{"name":"privateLinkServiceID","readOnly":true,"type":"ResourceId"},{"item":{"type":"string"},"name":"requiredMembers","type":"array<string>"},{"name":"type","type":"string"}],"type":"object"},"name":"privateLinkResources","type":"array<object>"},{"name":"provisioningState","readOnly":true,"type":"string"},{"enum":{"items":[{"value":"Disabled"},{"value":"Enabled"}]},"name":"publicNetworkAccess","type":"string"},{"name":"securityProfile","props":[{"name":"azureKeyVaultKms","props":[{"name":"enabled","type":"boolean"},{"name":"keyId","type":"string"},{"default":{"value":"Public"},"enum":{"items":[{"value":"Private"},{"value":"Public"}]},"name":"keyVaultNetworkAccess","type":"string"},{"name":"keyVaultResourceId","type":"string"}],"type":"object"},{"name":"defender","props":[{"name":"logAnalyticsWorkspaceResourceId","type":"ResourceId"},{"name":"securityMonitoring","props":[{"name":"enabled","type":"boolean"}],"type":"object"}],"type":"object"}],"type":"object"},{"name":"servicePrincipalProfile","props":[{"name":"clientId","required":true,"type":"string"},{"name":"secret","type":"string"}],"type":"object"},{"name":"storageProfile","props":[{"name":"diskCSIDriver","props":[{"name":"enabled","type":"boolean"}],"type":"object"},{"name":"fileCSIDriver","props":[{"name":"enabled","type":"boolean"}],"type":"object"},{"name":"snapshotController","props":[{"name":"enabled","type":"boolean"}],"type":"object"}],"type":"object"},{"name":"windowsProfile","props":[{"name":"adminPassword","type":"string"},{"name":"adminUsername","required":true,"type":"string"},{"name":"enableCSIProxy","type":"boolean"},{"name":"gmsaProfile","props":[{"name":"dnsServer","type":"string"},{"name":"enabled","type":"boolean"},{"name":"rootDomainName","type":"string"}],"type":"object"},{"enum":{"items":[{"value":"None"},{"value":"Windows_Server"}]},"name":"licenseType","type":"string"}],"type":"object"}],"type":"object"},{"name":"sku","props":[{"enum":{"items":[{"value":"Basic"}]},"name":"name","type":"string"},{"enum":{"items":[{"value":"Free"},{"value":"Paid"}]},"name":"tier","type":"string"}],"type":"object"},{"name":"systemData","props":[{"format":{"protocol":"iso"},"name":"createdAt","type":"dateTime"},{"name":"createdBy","type":"string"},{"enum":{"items":[{"value":"Application"},{"value":"Key"},{"value":"ManagedIdentity"},{"value":"User"}]},"name":"createdByType","type":"string"},{"format":{"protocol":"iso"},"name":"lastModifiedAt","type":"dateTime"},{"name":"lastModifiedBy","type":"string"},{"enum":{"items":[{"value":"Application"},{"value":"Key"},{"value":"ManagedIdentity"},{"value":"User"}]},"name":"lastModifiedByType","type":"string"}],"readOnly":true,"type":"object"},{"additionalProps":{"item":{"type":"string"}},"name":"tags","type":"object"},{"name":"type","readOnly":true,"type":"string"}],"type":"object"},"var":"$Instance"}},"statusCode":[200]},{"body":{"json":{"schema":{"type":"@ODataV4Format"}}},"isError":true},{"body":{"json":{"schema":{"type":"@MgmtErrorFormat"}}},"isError":true}]},"longRunning":{"finalStateVia":"azure-async-operation"},"operationId":"ManagedClusters_UpdateTags"}],"outputs":[{"clientFlatten":true,"ref":"$Instance","type":"object"}],"resources":[{"id":"/subscriptions/{}/resourcegroups/{}/providers/microsoft.containerservice/managedclusters/{}","plane":"mgmt-plane"}]}