{"argGroups":[{"args":[{"idPart":"name","options":["l","location"],"required":true,"type":"ResourceLocation","var":"$Path.location"},{"idPart":"subscription","options":["subscription"],"required":true,"type":"SubscriptionId","var":"$Path.subscriptionId"}],"name":""},{"args":[{"group":"Parameters","help":{"short":"The Data Lake Analytics name to check availability for."},"options":["name"],"required":true,"type":"string","var":"$parameters.name"},{"enum":{"items":[{"name":"Microsoft.DataLakeAnalytics/accounts","value":"Microsoft.DataLakeAnalytics/accounts"}]},"group":"Parameters","help":{"short":"The resource type. Note: This should not be set by the user, as the constant value is Microsoft.DataLakeAnalytics/accounts"},"options":["type"],"required":true,"type":"string","var":"$parameters.type"}],"name":"Parameters"}],"operations":[{"http":{"path":"/subscriptions/{subscriptionId}/providers/Microsoft.DataLakeAnalytics/locations/{location}/checkNameAvailability","request":{"body":{"json":{"schema":{"clientFlatten":true,"name":"parameters","props":[{"arg":"$parameters.name","name":"name","required":true,"type":"string"},{"arg":"$parameters.type","enum":{"items":[{"value":"Microsoft.DataLakeAnalytics/accounts"}]},"name":"type","required":true,"type":"string"}],"required":true,"type":"object"}}},"method":"post","path":{"params":[{"arg":"$Path.location","name":"location","required":true,"type":"string"},{"arg":"$Path.subscriptionId","name":"subscriptionId","required":true,"type":"string"}]},"query":{"consts":[{"const":true,"default":{"value":"2016-11-01"},"name":"api-version","readOnly":true,"required":true,"type":"string"}]}},"responses":[{"body":{"json":{"schema":{"props":[{"name":"message","readOnly":true,"type":"string"},{"name":"nameAvailable","readOnly":true,"type":"boolean"},{"name":"reason","readOnly":true,"type":"string"}],"type":"object"},"var":"$Instance"}},"statusCode":[200]},{"body":{"json":{"schema":{"type":"@MgmtErrorFormat"}}},"isError":true},{"body":{"json":{"schema":{"type":"@MgmtErrorFormat"}}},"isError":true}]},"operationId":"Accounts_CheckNameAvailability"}],"outputs":[{"clientFlatten":true,"ref":"$Instance","type":"object"}],"resources":[{"id":"/subscriptions/{}/providers/microsoft.datalakeanalytics/locations/{}/checknameavailability","plane":"mgmt-plane"}]}