{"argGroups":[{"args":[{"help":{"short":"The device name."},"idPart":"name","options":["device-name"],"required":true,"type":"string","var":"$Path.deviceName"},{"idPart":"resource_group","options":["g","resource-group"],"required":true,"type":"ResourceGroupName","var":"$Path.resourceGroupName"},{"idPart":"subscription","options":["subscription"],"required":true,"type":"SubscriptionId","var":"$Path.subscriptionId"}],"name":""}],"operations":[{"http":{"path":"/subscriptions/{subscriptionId}/resourceGroups/{resourceGroupName}/providers/Microsoft.DataBoxEdge/dataBoxEdgeDevices/{deviceName}/alerts","request":{"method":"get","path":{"params":[{"arg":"$Path.deviceName","name":"deviceName","required":true,"type":"string"},{"arg":"$Path.resourceGroupName","name":"resourceGroupName","required":true,"type":"string"},{"arg":"$Path.subscriptionId","name":"subscriptionId","required":true,"type":"string"}]},"query":{"consts":[{"const":true,"default":{"value":"2023-07-01"},"name":"api-version","readOnly":true,"required":true,"type":"string"}]}},"responses":[{"body":{"json":{"schema":{"props":[{"name":"nextLink","readOnly":true,"type":"string"},{"item":{"props":[{"format":{"template":"/subscriptions/{}/resourceGroups/{}/providers/Microsoft.DataBoxEdge/dataBoxEdgeDevices/{}/alerts/{}"},"name":"id","readOnly":true,"type":"ResourceId"},{"name":"name","readOnly":true,"type":"string"},{"clientFlatten":true,"name":"properties","props":[{"name":"alertType","readOnly":true,"type":"string"},{"format":{"protocol":"iso"},"name":"appearedAtDateTime","readOnly":true,"type":"dateTime"},{"additionalProps":{"item":{"type":"string"},"readOnly":true},"name":"detailedInformation","readOnly":true,"type":"object"},{"name":"errorDetails","props":[{"name":"errorCode","readOnly":true,"type":"string"},{"name":"errorMessage","readOnly":true,"type":"string"},{"name":"occurrences","readOnly":true,"type":"integer32"}],"readOnly":true,"type":"object"},{"name":"recommendation","readOnly":true,"type":"string"},{"enum":{"items":[{"value":"Critical"},{"value":"Informational"},{"value":"Warning"}]},"name":"severity","readOnly":true,"type":"string"},{"name":"title","readOnly":true,"type":"string"}],"readOnly":true,"type":"object"},{"name":"systemData","props":[{"format":{"protocol":"iso"},"name":"createdAt","type":"dateTime"},{"name":"createdBy","type":"string"},{"enum":{"items":[{"value":"Application"},{"value":"Key"},{"value":"ManagedIdentity"},{"value":"User"}]},"name":"createdByType","type":"string"},{"format":{"protocol":"iso"},"name":"lastModifiedAt","type":"dateTime"},{"name":"lastModifiedBy","type":"string"},{"enum":{"items":[{"value":"Application"},{"value":"Key"},{"value":"ManagedIdentity"},{"value":"User"}]},"name":"lastModifiedByType","type":"string"}],"readOnly":true,"type":"object"},{"name":"type","readOnly":true,"type":"string"}],"type":"object"},"name":"value","readOnly":true,"type":"array<object>"}],"type":"object"},"var":"$Instance"}},"statusCode":[200]},{"body":{"json":{"schema":{"type":"@ODataV4Format"}}},"isError":true},{"body":{"json":{"schema":{"type":"@MgmtErrorFormat"}}},"isError":true}]},"operationId":"Alerts_ListByDataBoxEdgeDevice"}],"outputs":[{"clientFlatten":true,"nextLink":"$Instance.nextLink","ref":"$Instance.value","type":"array"}],"resources":[{"id":"/subscriptions/{}/resourcegroups/{}/providers/microsoft.databoxedge/databoxedgedevices/{}/alerts","plane":"mgmt-plane"}]}