{"argGroups":[{"args":[{"help":{"short":"The name of the gateway."},"idPart":"name","options":["gateway-name"],"required":true,"type":"string","var":"$Path.gatewayName"},{"help":{"short":"The name of the nat rule."},"idPart":"child_name_1","options":["n","name","nat-rule-name"],"required":true,"type":"string","var":"$Path.natRuleName"},{"idPart":"resource_group","options":["g","resource-group"],"required":true,"type":"ResourceGroupName","var":"$Path.resourceGroupName"},{"idPart":"subscription","options":["subscription"],"required":true,"type":"SubscriptionId","var":"$Path.subscriptionId"}],"name":""},{"args":[{"format":{"template":"/subscriptions/{}/resourceGroups/{}/providers/Microsoft.Network/vpnGateways/{}/natRules/{}"},"group":"NatRuleParameters","help":{"short":"Resource ID."},"hide":true,"nullable":true,"options":["id"],"type":"ResourceId","var":"$NatRuleParameters.id"}],"name":"NatRuleParameters"},{"args":[{"group":"Properties","help":{"short":"The private IP address external mapping for NAT."},"item":{"nullable":true,"type":"@VpnNatRuleMapping_update"},"nullable":true,"options":["external-mappings"],"type":"array<@VpnNatRuleMapping_update>","var":"$NatRuleParameters.properties.externalMappings"},{"group":"Properties","help":{"short":"The private IP address internal mapping for NAT."},"item":{"args":[{"help":{"short":"Address space for Vpn NatRule mapping."},"nullable":true,"options":["address-space"],"type":"string","var":"@VpnNatRuleMapping_update.addressSpace"},{"help":{"short":"Port range for Vpn NatRule mapping."},"nullable":true,"options":["port-range"],"type":"string","var":"@VpnNatRuleMapping_update.portRange"}],"cls":"VpnNatRuleMapping_update","nullable":true,"type":"object"},"nullable":true,"options":["internal-mappings"],"type":"array<object>","var":"$NatRuleParameters.properties.internalMappings"},{"group":"Properties","help":{"short":"The IP Configuration ID this NAT rule applies to."},"nullable":true,"options":["ip-configuration-id"],"type":"string","var":"$NatRuleParameters.properties.ipConfigurationId"},{"enum":{"items":[{"name":"EgressSnat","value":"EgressSnat"},{"name":"IngressSnat","value":"IngressSnat"}]},"group":"Properties","help":{"short":"The Source NAT direction of a VPN NAT."},"nullable":true,"options":["mode"],"type":"string","var":"$NatRuleParameters.properties.mode"},{"enum":{"items":[{"name":"Dynamic","value":"Dynamic"},{"name":"Static","value":"Static"}]},"group":"Properties","help":{"short":"The type of NAT rule for VPN NAT."},"nullable":true,"options":["type"],"type":"string","var":"$NatRuleParameters.properties.type"}],"name":"Properties"}],"operations":[{"http":{"path":"/subscriptions/{subscriptionId}/resourceGroups/{resourceGroupName}/providers/Microsoft.Network/vpnGateways/{gatewayName}/natRules/{natRuleName}","request":{"method":"get","path":{"params":[{"arg":"$Path.gatewayName","name":"gatewayName","required":true,"type":"string"},{"arg":"$Path.natRuleName","name":"natRuleName","required":true,"type":"string"},{"arg":"$Path.resourceGroupName","name":"resourceGroupName","required":true,"type":"string"},{"arg":"$Path.subscriptionId","name":"subscriptionId","required":true,"type":"string"}]},"query":{"consts":[{"const":true,"default":{"value":"2024-05-01"},"name":"api-version","readOnly":true,"required":true,"type":"string"}]}},"responses":[{"body":{"json":{"schema":{"cls":"VpnGatewayNatRule_read","props":[{"name":"etag","readOnly":true,"type":"string"},{"format":{"template":"/subscriptions/{}/resourceGroups/{}/providers/Microsoft.Network/vpnGateways/{}/natRules/{}"},"name":"id","type":"ResourceId"},{"name":"name","type":"string"},{"clientFlatten":true,"name":"properties","props":[{"item":{"cls":"SubResource_read","props":[{"name":"id","type":"string"}],"type":"object"},"name":"egressVpnSiteLinkConnections","readOnly":true,"type":"array<object>"},{"item":{"type":"@VpnNatRuleMapping_read"},"name":"externalMappings","type":"array<@VpnNatRuleMapping_read>"},{"item":{"type":"@SubResource_read"},"name":"ingressVpnSiteLinkConnections","readOnly":true,"type":"array<@SubResource_read>"},{"item":{"cls":"VpnNatRuleMapping_read","props":[{"name":"addressSpace","type":"string"},{"name":"portRange","type":"string"}],"type":"object"},"name":"internalMappings","type":"array<object>"},{"name":"ipConfigurationId","type":"string"},{"enum":{"items":[{"value":"EgressSnat"},{"value":"IngressSnat"}]},"name":"mode","type":"string"},{"enum":{"items":[{"value":"Deleting"},{"value":"Failed"},{"value":"Succeeded"},{"value":"Updating"}]},"name":"provisioningState","readOnly":true,"type":"string"},{"enum":{"items":[{"value":"Dynamic"},{"value":"Static"}]},"name":"type","type":"string"}],"type":"object"},{"name":"type","readOnly":true,"type":"string"}],"type":"object"},"var":"$Instance"}},"statusCode":[200]},{"body":{"json":{"schema":{"type":"@ODataV4Format"}}},"isError":true}]},"operationId":"NatRules_Get"},{"instanceUpdate":{"json":{"schema":{"clientFlatten":true,"name":"NatRuleParameters","props":[{"arg":"$NatRuleParameters.id","format":{"template":"/subscriptions/{}/resourceGroups/{}/providers/Microsoft.Network/vpnGateways/{}/natRules/{}"},"name":"id","type":"ResourceId"},{"arg":"$Path.natRuleName","name":"name","type":"string"},{"clientFlatten":true,"name":"properties","props":[{"arg":"$NatRuleParameters.properties.externalMappings","item":{"type":"@VpnNatRuleMapping_update"},"name":"externalMappings","type":"array<@VpnNatRuleMapping_update>"},{"arg":"$NatRuleParameters.properties.internalMappings","item":{"cls":"VpnNatRuleMapping_update","props":[{"arg":"@VpnNatRuleMapping_update.addressSpace","name":"addressSpace","type":"string"},{"arg":"@VpnNatRuleMapping_update.portRange","name":"portRange","type":"string"}],"type":"object"},"name":"internalMappings","type":"array<object>"},{"arg":"$NatRuleParameters.properties.ipConfigurationId","name":"ipConfigurationId","type":"string"},{"arg":"$NatRuleParameters.properties.mode","enum":{"items":[{"value":"EgressSnat"},{"value":"IngressSnat"}]},"name":"mode","type":"string"},{"arg":"$NatRuleParameters.properties.type","enum":{"items":[{"value":"Dynamic"},{"value":"Static"}]},"name":"type","type":"string"}],"type":"object"}],"required":true,"type":"object"}},"ref":"$Instance"}},{"http":{"path":"/subscriptions/{subscriptionId}/resourceGroups/{resourceGroupName}/providers/Microsoft.Network/vpnGateways/{gatewayName}/natRules/{natRuleName}","request":{"body":{"json":{"ref":"$Instance"}},"method":"put","path":{"params":[{"arg":"$Path.gatewayName","name":"gatewayName","required":true,"type":"string"},{"arg":"$Path.natRuleName","name":"natRuleName","required":true,"type":"string"},{"arg":"$Path.resourceGroupName","name":"resourceGroupName","required":true,"type":"string"},{"arg":"$Path.subscriptionId","name":"subscriptionId","required":true,"type":"string"}]},"query":{"consts":[{"const":true,"default":{"value":"2024-05-01"},"name":"api-version","readOnly":true,"required":true,"type":"string"}]}},"responses":[{"body":{"json":{"schema":{"type":"@VpnGatewayNatRule_read"},"var":"$Instance"}},"statusCode":[200,201]},{"body":{"json":{"schema":{"type":"@ODataV4Format"}}},"isError":true}]},"longRunning":{"finalStateVia":"azure-async-operation"},"operationId":"NatRules_CreateOrUpdate"}],"outputs":[{"clientFlatten":true,"ref":"$Instance","type":"object"}],"resources":[{"id":"/subscriptions/{}/resourcegroups/{}/providers/microsoft.network/vpngateways/{}/natrules/{}","plane":"mgmt-plane"}]}